[
  {
    "name": "Europe",
    "children": [
      {
        "name": "España",
        "children": [
          {
            "name": "Andalucía",
            "children": []
          },
          {
            "name": "Aragón",
            "children": []
          },
          {
            "name": "Asturias",
            "children": []
          },
          {
            "name": "Baleares",
            "children": []
          },
          {
            "name": "Canarias",
            "children": []
          },
          {
            "name": "Cataluña",
            "children": []
          },
          {
            "name": "Cantabria",
            "children": []
          },
          {
            "name": "Castilla León",
            "children": []
          },
          {
            "name": "Castilla La Mancha",
            "children": []
          },
          {
            "name": "Extremadura",
            "children": []
          },
          {
            "name": "País Vasco",
            "children": []
          },
          {
            "name": "Galicia",
            "children": []
          },
          {
            "name": "La Rioja",
            "children": []
          },
          {
            "name": "Madrid",
            "children": [
              {
                "name": "Madrid",
                "children": []
              }
            ]
          },
          {
            "name": "Ceuta",
            "children": []
          },
          {
            "name": "Melilla",
            "children": []
          },
          {
            "name": "Murcia",
            "children": []
          },
          {
            "name": "Navarra",
            "children": []
          },
          {
            "name": "Valencia",
            "children": []
          }
        ]
      },
      {
        "name": "Alemania",
        "children": []
      },
      {
        "name": "Austria",
        "children": []
      },
      {
        "name": "Belgica",
        "children": []
      },
      {
        "name": "Bulgaria",
        "children": []
      },
      {
        "name": "Checoslovaquia",
        "children": []
      },
      {
        "name": "Chipre",
        "children": []
      },
      {
        "name": "Dinamarca",
        "children": []
      },
      {
        "name": "Eslovenia",
        "children": []
      },
      {
        "name": "Finlandia",
        "children": []
      },
      {
        "name": "Francia",
        "children": []
      },
      {
        "name": "Gran Bretaña",
        "children": []
      },
      {
        "name": "Grecia",
        "children": []
      },
      {
        "name": "Holanda",
        "children": []
      },
      {
        "name": "Hungria",
        "children": []
      },
      {
        "name": "Islandia Y Groenlandia",
        "children": []
      },
      {
        "name": "Italia",
        "children": []
      },
      {
        "name": "Noruega",
        "children": []
      },
      {
        "name": "Polonia",
        "children": []
      },
      {
        "name": "Portugal",
        "children": []
      },
      {
        "name": "Rumania",
        "children": []
      },
      {
        "name": "Rusia",
        "children": []
      },
      {
        "name": "Suecia",
        "children": []
      },
      {
        "name": "Yugoslavia",
        "children": []
      }
    ]
  },
  {
    "name": "America",
    "children": [
      {
        "name": "Argentina",
        "children": []
      },
      {
        "name": "Bolivia",
        "children": []
      },
      {
        "name": "Brasil",
        "children": []
      },
      {
        "name": "Canada",
        "children": []
      },
      {
        "name": "Costa Rica",
        "children": []
      },
      {
        "name": "Chile",
        "children": []
      },
      {
        "name": "Colombia",
        "children": []
      },
      {
        "name": "Cuba",
        "children": []
      },
      {
        "name": "Ecuador",
        "children": []
      },
      {
        "name": "Mexico",
        "children": []
      },
      {
        "name": "Peru",
        "children": []
      },
      {
        "name": "USA",
        "children": [
          {
            "name": "INDIANA",
            "children": []
          },
          {
            "name": "ARKANSAS",
            "children": []
          },
          {
            "name": "MAINE",
            "children": []
          },
          {
            "name": "MISSOURI",
            "children": []
          },
          {
            "name": "MINNESOTA",
            "children": []
          },
          {
            "name": "IOWA",
            "children": []
          },
          {
            "name": "MINESOTA",
            "children": []
          },
          {
            "name": "KANSAS",
            "children": []
          },
          {
            "name": "FLORIDA",
            "children": []
          },
          {
            "name": "MASSACHUSETTS",
            "children": []
          },
          {
            "name": "VIRGINIA",
            "children": []
          },
          {
            "name": "RHODE ISLAND",
            "children": []
          },
          {
            "name": "NEW JERSEY",
            "children": []
          },
          {
            "name": "NEW YORK",
            "children": []
          },
          {
            "name": "PENNSYLVANIA",
            "children": []
          },
          {
            "name": "MARYLAND",
            "children": []
          },
          {
            "name": "DELAWERE",
            "children": []
          },
          {
            "name": "NORTH CAROLINA",
            "children": []
          },
          {
            "name": "GEORGIA",
            "children": []
          },
          {
            "name": "TENNESSEE",
            "children": []
          },
          {
            "name": "KENTUCKY",
            "children": []
          },
          {
            "name": "TEXAS",
            "children": []
          },
          {
            "name": "WASHINGTON",
            "children": []
          },
          {
            "name": "LOUISIANA",
            "children": []
          },
          {
            "name": "CALIFORNIA",
            "children": []
          },
          {
            "name": "OKLAHOMA",
            "children": []
          },
          {
            "name": "OHIO",
            "children": []
          },
          {
            "name": "MICHIGAN",
            "children": []
          },
          {
            "name": "ILLINOIS",
            "children": []
          },
          {
            "name": "WISCONSIN",
            "children": []
          },
          {
            "name": "CONNECTICUT",
            "children": []
          },
          {
            "name": "ALABAMA",
            "children": []
          },
          {
            "name": "PENSILVANIA",
            "children": []
          },
          {
            "name": "PUERTO RICO",
            "children": []
          },
          {
            "name": "CAROLINA",
            "children": []
          },
          {
            "name": "OREGON",
            "children": []
          }
        ]
      },
      {
        "name": "Venezuela",
        "children": []
      }
    ]
  },
  {
    "name": "Asia",
    "children": [
      {
        "name": "Bahrain",
        "children": []
      },
      {
        "name": "India",
        "children": []
      },
      {
        "name": "Indonesia",
        "children": []
      },
      {
        "name": "Israel",
        "children": []
      },
      {
        "name": "Japón",
        "children": []
      },
      {
        "name": "Libano",
        "children": []
      },
      {
        "name": "Malasia",
        "children": []
      },
      {
        "name": "Oman",
        "children": []
      },
      {
        "name": "Qatar",
        "children": []
      },
      {
        "name": "Turquia",
        "children": []
      }
    ]
  },
  {
    "name": "Africa",
    "children": [
      {
        "name": "SUDAFRICA",
        "children": []
      },
      {
        "name": "ARGELIA",
        "children": []
      },
      {
        "name": "MARRUECOS",
        "children": []
      }
    ]
  },
  {
    "name": "Oceania",
    "children": [
      {
        "name": "AUSTRALIA",
        "children": []
      },
      {
        "name": "NUEVA ZELANDA",
        "children": []
      }
    ]
  }
]